cvxpnpl.py
cvxpnpl-1.1.0.dist-info/LICENSE
cvxpnpl-1.1.0.dist-info/METADATA
cvxpnpl-1.1.0.dist-info/WHEEL
cvxpnpl-1.1.0.dist-info/top_level.txt
cvxpnpl-1.1.0.dist-info/RECORD
