Metadata-Version: 2.1
Name: cvxpnpl
Version: 1.1.0
Summary: A convex Perspective-n-Points-and-Lines method.
Home-page: https://github.com/SergioRAgostinho/cvxpnpl
Author: Sérgio Agostinho
Author-email: sergio@sergioagostinho.com
License: Apache 2.0
Platform: UNKNOWN
Classifier: License :: OSI Approved :: Apache Software License
Classifier: Operating System :: OS Independent
Classifier: Programming Language :: Python :: 3
Classifier: Programming Language :: Python :: 3.5
Classifier: Programming Language :: Python :: 3.6
Classifier: Programming Language :: Python :: 3.7
Classifier: Programming Language :: Python :: 3.8
Classifier: Programming Language :: Python :: 3 :: Only
Classifier: Topic :: Scientific/Engineering
Requires-Python: >=3.5
License-File: LICENSE
Requires-Dist: packaging
Requires-Dist: numpy
Requires-Dist: scipy
Requires-Dist: scs (>=2.0.0)
